{
    "dagny_lifetest": {
        "memories": [
            {
                "id": "mem_1767850924",
                "content": "Built the Lifeline module today.",
                "timestamp": 1767850924.836799
            }
        ],
        "ops": {
            "cleaning": [
                {
                    "id": "op_1767850924",
                    "content": "Clean the workshop",
                    "status": "done",
                    "timestamp": 1767850924.868835
                }
            ],
            "bills": [],
            "meals": []
        },
        "favors": [
            {
                "id": "favor_1767850924",
                "content": "Prepare breakfast for tomorrow Dagny",
                "status": "pending",
                "timestamp": 1767850924.8818
            }
        ],
        "zen_cycles": 1
    }
}